bswrapper/__init__.py
bswrapper/bswrapper.py
bswrapper/exceptions.py
bswrapper-0.2.2.dist-info/licenses/LICENSE
bswrapper-0.2.2.dist-info/METADATA
bswrapper-0.2.2.dist-info/WHEEL
bswrapper-0.2.2.dist-info/top_level.txt
bswrapper-0.2.2.dist-info/RECORD
