Metadata-Version: 2.4
Name: bswrapper
Version: 0.2.2
Summary: An easy to use API Wrapper for the Brawl Stars API
Author-email: BigPattyOG <ptfaint@gmail.com>
License-Expression: MIT
Project-URL: Repository, https://github.com/BigPattyOG/bswrapper
Classifier: Programming Language :: Python :: 3
Classifier: Operating System :: OS Independent
Requires-Python: >=3.12
License-File: LICENSE
Requires-Dist: requests
Dynamic: license-file
